dlcalc/__init__.py
dlcalc/modeling.py
dlcalc/samples_per_sec_to_mfu.py
dlcalc/samples_per_sec_to_tokens_per_day.py
dlcalc/summarize_checkpoint.py
dlcalc/topology_evaluate.py
dlcalc/topology_scheduler.py
dlcalc/topology_visualizer.py
dlcalc/training_3d.py
dlcalc/utils/__init__.py
dlcalc/utils/comms.py
dlcalc/utils/compute.py
dlcalc/utils/configurations.py
dlcalc/utils/data.py
dlcalc/utils/hardware.py
dlcalc/utils/math.py
dlcalc/utils/model_3d.py
dlcalc/utils/printing.py
dlcalc/utils/cluster/__init__.py
dlcalc/utils/cluster/ec2.py
dlcalc/utils/cluster/kubernetes.py
dlcalc/utils/cluster/topology.py
dlcalc-0.2.0.dist-info/METADATA
dlcalc-0.2.0.dist-info/WHEEL
dlcalc-0.2.0.dist-info/entry_points.txt
dlcalc-0.2.0.dist-info/licenses/LICENSE
dlcalc-0.2.0.dist-info/RECORD
