Metadata-Version: 2.4
Name: dlcalc
Version: 0.2.0
Author-email: Justin Chiu <jfc4050@gmail.com>
License-File: LICENSE
Requires-Python: >=3.9
Requires-Dist: boto3==1.34.133
Requires-Dist: kubernetes==30.1.0
Requires-Dist: pyvis==0.3.2
Requires-Dist: pyyaml>=6.0.1
Requires-Dist: tqdm==4.66.4
Provides-Extra: dev
Requires-Dist: mypy>=1.10.0; extra == 'dev'
Requires-Dist: pre-commit>=3.7.0; extra == 'dev'
Requires-Dist: pytest-cov>=5.0.0; extra == 'dev'
Requires-Dist: pytest-mock>=3.14.0; extra == 'dev'
Requires-Dist: pytest>=8.0.0; extra == 'dev'
Requires-Dist: ruff>=0.4.3; extra == 'dev'
